error_propagation/__init__.py
error_propagation/core.py
error_propagation/finance/__init__.py
error_propagation/finance/npv.py
error_propagation-0.0.4.dist-info/LICENSE
error_propagation-0.0.4.dist-info/METADATA
error_propagation-0.0.4.dist-info/WHEEL
error_propagation-0.0.4.dist-info/top_level.txt
error_propagation-0.0.4.dist-info/RECORD
