Metadata-Version: 2.1
Name: error-propagation
Version: 0.0.4
Summary: Package that computes error propagation
Home-page: https://github.com/davidreissmello/error_propagation
Author: David Reiss-Mello
Author-email: davidreissmello@gmail.com
License: UNKNOWN
Platform: UNKNOWN
License-File: LICENSE
